odoo/addons/ssi_project_type/README.rst
odoo/addons/ssi_project_type/__init__.py
odoo/addons/ssi_project_type/__manifest__.py
odoo/addons/ssi_project_type/models/__init__.py
odoo/addons/ssi_project_type/models/project_project.py
odoo/addons/ssi_project_type/models/project_type.py
odoo/addons/ssi_project_type/security/ir.model.access.csv
odoo/addons/ssi_project_type/security/res_group_data.xml
odoo/addons/ssi_project_type/static/description/icon.png
odoo/addons/ssi_project_type/views/project_project_views.xml
odoo/addons/ssi_project_type/views/project_type_views.xml
odoo14_addon_ssi_project_type-14.0.1.3.0.dist-info/METADATA
odoo14_addon_ssi_project_type-14.0.1.3.0.dist-info/WHEEL
odoo14_addon_ssi_project_type-14.0.1.3.0.dist-info/top_level.txt
odoo14_addon_ssi_project_type-14.0.1.3.0.dist-info/RECORD
